pyjsg/__init__.py
pyjsg/validate_json.py
pyjsg/jsglib/README.md
pyjsg/jsglib/__init__.py
pyjsg/jsglib/conformance.py
pyjsg/jsglib/empty.py
pyjsg/jsglib/jsg_anytype.py
pyjsg/jsglib/jsg_array.py
pyjsg/jsglib/jsg_context.py
pyjsg/jsglib/jsg_null.py
pyjsg/jsglib/jsg_object.py
pyjsg/jsglib/jsg_objectmap.py
pyjsg/jsglib/jsg_strings.py
pyjsg/jsglib/jsg_validateable.py
pyjsg/jsglib/loader.py
pyjsg/jsglib/logger.py
pyjsg/jsglib/typing_patch_36.py
pyjsg/jsglib/typing_patch_37.py
pyjsg/parser/__init__.py
pyjsg/parser/jsgLexer.interp
pyjsg/parser/jsgLexer.py
pyjsg/parser/jsgLexer.tokens
pyjsg/parser/jsgParser.interp
pyjsg/parser/jsgParser.py
pyjsg/parser/jsgParser.tokens
pyjsg/parser/jsgParserLexer.py
pyjsg/parser/jsgParserLexer.tokens
pyjsg/parser/jsgParserParser.py
pyjsg/parser/jsgParserVisitor.py
pyjsg/parser_impl/__init__.py
pyjsg/parser_impl/anonymousidentifierfactory.py
pyjsg/parser_impl/generate_python.py
pyjsg/parser_impl/jsg_arrayexpr_parser.py
pyjsg/parser_impl/jsg_builtinvaluetype_parser.py
pyjsg/parser_impl/jsg_doc_context.py
pyjsg/parser_impl/jsg_doc_parser.py
pyjsg/parser_impl/jsg_ebnf_parser.py
pyjsg/parser_impl/jsg_lexerruleblock_parser.py
pyjsg/parser_impl/jsg_objectexpr_parser.py
pyjsg/parser_impl/jsg_pairdef_parser.py
pyjsg/parser_impl/jsg_valuetype_parser.py
pyjsg/parser_impl/parser_utils.py
PyJSG-0.11.10.dist-info/AUTHORS
PyJSG-0.11.10.dist-info/METADATA
PyJSG-0.11.10.dist-info/WHEEL
PyJSG-0.11.10.dist-info/entry_points.txt
PyJSG-0.11.10.dist-info/pbr.json
PyJSG-0.11.10.dist-info/top_level.txt
PyJSG-0.11.10.dist-info/RECORD
